tsinterface/io/bbox_io.py
tsinterface/io/detection_io.py
tsinterface/io/distribution_io.py
tsinterface/io/info_dto.py
tsinterface/io/io.py
tsinterface/io/label_io.py
tsinterface/schema/load_output_schema.json
tsinterface/schema/process_input_schema.json
tsinterface/schema/process_output_schema.json
tsinterface/schema/validation_output_schema.json
tsinterface/ts_interface.py
ts_interface-0.1.4.dist-info/LICENSE
ts_interface-0.1.4.dist-info/METADATA
ts_interface-0.1.4.dist-info/WHEEL
ts_interface-0.1.4.dist-info/RECORD
