Metadata-Version: 2.1
Name: ts-interface
Version: 0.1.4
Summary: 
Author: ph
Author-email: ph@tordenskjold.space
Requires-Python: >=3.8,<4.0
Classifier: Programming Language :: Python :: 3
Classifier: Programming Language :: Python :: 3.8
Classifier: Programming Language :: Python :: 3.9
Classifier: Programming Language :: Python :: 3.10
Classifier: Programming Language :: Python :: 3.11
Classifier: Programming Language :: Python :: 3.12
Requires-Dist: jsonschema (>=4.22.0,<5.0.0)
